{
	"info": {
		"_postman_id": "simple-mp3-api",
		"name": "MP3 API Simple",
		"schema": "https://schema.getpostman.com/json/collection/v2.1.0/collection.json"
	},
	"item": [
		{
			"name": "Get All Users",
			"request": {
				"method": "GET",
				"header": [],
				"url": {
					"raw": "http://localhost:3000/api/users",
					"protocol": "http",
					"host": ["localhost"],
					"port": "3000",
					"path": ["api", "users"]
				}
			}
		},
		{
			"name": "Create User",
			"request": {
				"method": "POST",
				"header": [
					{
						"key": "Content-Type",
						"value": "application/json"
					}
				],
				"body": {
					"mode": "raw",
					"raw": "{\n    \"name\": \"John Doe\",\n    \"email\": \"john@example.com\"\n}"
				},
				"url": {
					"raw": "http://localhost:3000/api/users",
					"protocol": "http",
					"host": ["localhost"],
					"port": "3000",
					"path": ["api", "users"]
				}
			}
		},
		{
			"name": "Get User by ID",
			"request": {
				"method": "GET",
				"header": [],
				"url": {
					"raw": "http://localhost:3000/api/users/:id",
					"protocol": "http",
					"host": ["localhost"],
					"port": "3000",
					"path": ["api", "users", ":id"]
				}
			}
		},
		{
			"name": "Update User",
			"request": {
				"method": "PUT",
				"header": [
					{
						"key": "Content-Type",
						"value": "application/json"
					}
				],
				"body": {
					"mode": "raw",
					"raw": "{\n    \"name\": \"Jane Doe\",\n    \"email\": \"jane@example.com\",\n    \"pendingTasks\": []\n}"
				},
				"url": {
					"raw": "http://localhost:3000/api/users/:id",
					"protocol": "http",
					"host": ["localhost"],
					"port": "3000",
					"path": ["api", "users", ":id"]
				}
			}
		},
		{
			"name": "Delete User",
			"request": {
				"method": "DELETE",
				"header": [],
				"url": {
					"raw": "http://localhost:3000/api/users/:id",
					"protocol": "http",
					"host": ["localhost"],
					"port": "3000",
					"path": ["api", "users", ":id"]
				}
			}
		},
		{
			"name": "Get All Tasks",
			"request": {
				"method": "GET",
				"header": [],
				"url": {
					"raw": "http://localhost:3000/api/tasks",
					"protocol": "http",
					"host": ["localhost"],
					"port": "3000",
					"path": ["api", "tasks"]
				}
			}
		},
		{
			"name": "Create Task",
			"request": {
				"method": "POST",
				"header": [
					{
						"key": "Content-Type",
						"value": "application/json"
					}
				],
				"body": {
					"mode": "raw",
					"raw": "{\n    \"name\": \"Complete assignment\",\n    \"description\": \"Finish the MP3 project\",\n    \"deadline\": \"2025-12-31T23:59:59Z\",\n    \"completed\": false\n}"
				},
				"url": {
					"raw": "http://localhost:3000/api/tasks",
					"protocol": "http",
					"host": ["localhost"],
					"port": "3000",
					"path": ["api", "tasks"]
				}
			}
		},
		{
			"name": "Get Task by ID",
			"request": {
				"method": "GET",
				"header": [],
				"url": {
					"raw": "http://localhost:3000/api/tasks/:id",
					"protocol": "http",
					"host": ["localhost"],
					"port": "3000",
					"path": ["api", "tasks", ":id"]
				}
			}
		},
		{
			"name": "Update Task",
			"request": {
				"method": "PUT",
				"header": [
					{
						"key": "Content-Type",
						"value": "application/json"
					}
				],
				"body": {
					"mode": "raw",
					"raw": "{\n    \"name\": \"Updated task\",\n    \"description\": \"Updated description\",\n    \"deadline\": \"2025-12-31T23:59:59Z\",\n    \"completed\": true\n}"
				},
				"url": {
					"raw": "http://localhost:3000/api/tasks/:id",
					"protocol": "http",
					"host": ["localhost"],
					"port": "3000",
					"path": ["api", "tasks", ":id"]
				}
			}
		},
		{
			"name": "Delete Task",
			"request": {
				"method": "DELETE",
				"header": [],
				"url": {
					"raw": "http://localhost:3000/api/tasks/:id",
					"protocol": "http",
					"host": ["localhost"],
					"port": "3000",
					"path": ["api", "tasks", ":id"]
				}
			}
		},
		{
			"name": "Get Completed Tasks",
			"request": {
				"method": "GET",
				"header": [],
				"url": {
					"raw": "http://localhost:3000/api/tasks?where={\"completed\":true}",
					"protocol": "http",
					"host": ["localhost"],
					"port": "3000",
					"path": ["api", "tasks"],
					"query": [
						{
							"key": "where",
							"value": "{\"completed\":true}"
						}
					]
				}
			}
		},
		{
			"name": "Get Users Sorted",
			"request": {
				"method": "GET",
				"header": [],
				"url": {
					"raw": "http://localhost:3000/api/users?sort={\"name\":1}",
					"protocol": "http",
					"host": ["localhost"],
					"port": "3000",
					"path": ["api", "users"],
					"query": [
						{
							"key": "sort",
							"value": "{\"name\":1}"
						}
					]
				}
			}
		}
	]
}

